{
  "name": "@wazoo/worlds-ai-sdk",
  "version": "0.0.1",

  "exports": {
    ".": "./src/mod.ts",
    "./tools/sparql": "./src/tools/sparql.ts",
    "./tools/search": "./src/tools/search.ts",
    "./tools/list-world": "./src/tools/list-world.ts",
    "./tools/get-world": "./src/tools/get-world.ts",
    "./tools/create-world": "./src/tools/create-world.ts",
    "./tools/update-world": "./src/tools/update-world.ts",
    "./tools/delete-world": "./src/tools/delete-world.ts",
    "./tools/import": "./src/tools/import.ts",
    "./tools/export": "./src/tools/export.ts",

    "./types": "./src/types.ts"
  },
  "imports": {
    "#/": "./src/"
  },
  "tasks": {
    "test": "deno test -A"
  },
  "publish": {
    "exclude": ["**/*.test.ts", "**/*_test.ts"]
  }
}
